Lab 05/group19_lab5_part4/ALU.v
/*
Group 19
Lab05 - Part01
*/

/*===========================================================
                    ALU MODULE
=============================================================*/

module ALU (DATA1 , DATA2 , RESULT , SELECT,ZERO);
    input[7:0] DATA1,DATA2;
    input[2:0] SELECT ;
    output reg[7:0] RESULT ;
    output reg ZERO;

    /*Temporaray wires to get the result of each instances*/
    wire[7:0] resultFORWARD , resultADD , resultAND , resultOR;

    /*Creating instances*/
    Forward forward1(DATA2,resultFORWARD) ;
    ADD add1(DATA1,DATA2,resultADD) ;
    AND and1(DATA1 , DATA2 , resultAND) ;
    OR or1(DATA1 , DATA2 , resultOR) ;

    /*If there is a change is selection this will execute*/
    always @(SELECT,DATA1,DATA2) begin

        case(SELECT)

            /*Case for Forwarding*/
            3'b000 :  assign RESULT = resultFORWARD;

            /*Case for Addition*/
            3'b001 :  assign RESULT = resultADD ;

            /*Case for bitwise AND operation*/
            3'b010 :  assign RESULT = resultAND ;

            /*Case for bitwise OR Operation*/
            3'b011 :  assign RESULT = resultOR ;

            default : assign RESULT = 8'bx;

        endcase
    end

    always @(DATA1,DATA2,SELECT,resultADD) begin
        if(resultADD == 8'b0) begin
            ZERO = 1 ;
        end
        else begin
            ZERO = 0;
        end
    end
endmodule

/*===========================================================
                    FORWARD MODULE
=============================================================*/

module Forward (DATA2,RESULT);
    input [7:0] DATA2;
    output [7:0] RESULT ;

    /**Update the RESULT with the value in DATA2*/
    assign #1 RESULT = DATA2;
    
endmodule

/*=============================================================
                    ADD MODULE
===============================================================*/

module ADD (DATA1 , DATA2 , RESULT);
    
    input [7:0] DATA1 , DATA2 ;
    output signed [7:0] RESULT ;

    /*Update the RESULT with the addition of DATA1 and DATA2*/
    assign #2 RESULT = DATA1 + DATA2 ;
endmodule

/*===============================================================
                        AND MODULE
=================================================================*/

module AND (DATA1 , DATA2 , RESULT);
    input [7:0] DATA1 , DATA2 ;
    output [7:0] RESULT ;

    /*Update the RESULT with the bitwise and operation between DATA1 and DATA2*/
    assign #1 RESULT = DATA1 & DATA2 ;
endmodule

/*===============================================================
                        OR MODULE
=================================================================*/

module OR (DATA1 , DATA2 , RESULT);
    input [7:0] DATA1 , DATA2 ;
    output [7:0] RESULT ;

    /*Update the RESULT with the bitwise and operation between DATA1 and DATA2*/
    assign #1 RESULT = DATA1 | DATA2 ;
endmodule

Lab 05/group19_lab5_part4/cpu.v
`include "reg.v"
`include "ALU.v"

/*------------------------
        CPU MODULE
-------------------------*/

module cpu (PC,INSTRUCTION,CLK,RESET);
    output[31:0] PC;
    input[31:0] INSTRUCTION;
    input CLK,RESET;
    reg[7:0] OPCODE;

    wire[7:0] OUT1;
    wire[7:0] OUT2;
    reg[7:0] IMMEDIATE;
    reg[7:0] OFFSET;

    reg[2:0] READREG1;
    reg[2:0] READREG2;
    reg[2:0] WRITEREG;

    wire WRITE_ENABLE;
    wire MUX1SELECT;
    wire MUX2SELECT;
    wire[2:0] ALUOP;
    
    wire[7:0] NEG;
    wire[7:0] MUX1OUT;
    wire[7:0] MUX2OUT;
    wire[7:0] ALURESULT;
    wire[7:0] IN;
    
    wire BRANCH_ENABLE;
    wire JUMP_ENABLE;
    wire[31:0] EXTENDED;
    wire[9:0] SHIFTED;
    
    always @(INSTRUCTION) begin
        OPCODE = INSTRUCTION[31:24];
        WRITEREG = INSTRUCTION[18:16];
        READREG1 = INSTRUCTION[10:8];
        READREG2 = INSTRUCTION[2:0];
        IMMEDIATE = INSTRUCTION[7:0];
        OFFSET = INSTRUCTION[23:16];
    end

    /*Extended the offset*/
    Extend ex(SHIFTED,EXTENDED);

    /*Shift the offset by 2*/
    ShiftLeft sl(OFFSET,SHIFTED);

    /*Module to update the PC*/
    BranchAdder beqadder(PC,CLK,RESET,EXTENDED,BRANCH_SELECT,JUMP_ENABLE);

    /*Module to get the BRACH_SELECT value*/
    ANDMODULE andmodule(ZERO,BRANCH_ENABLE,BRANCH_SELECT);
    
    /*reg_file instantiation*/
    reg_file register(ALURESULT,OUT1,OUT2,WRITEREG,READREG1,READREG2,WRITE_ENABLE,CLK,RESET);

    /*Control Unit instantiation*/
    ControlUnit cu(OPCODE,WRITE_ENABLE,MUX1SELECT,MUX2SELECT,BRANCH_ENABLE,JUMP_ENABLE,ALUOP);
    
    /*TWOS compliment module instantiation*/
    TWOS_COMPLIMENT f1(OUT2,NEG);

    /*MUX 1 instantiation */
    MUX m1(OUT2,NEG,MUX1OUT,MUX1SELECT);

    /*MUX2 instantiation*/
    MUX m2(IMMEDIATE,MUX1OUT,MUX2OUT,MUX2SELECT);

    /*ALU module instantiation*/
    ALU alu(OUT1,MUX2OUT,ALURESULT,ALUOP,ZERO);  
    
endmodule

/*------------------------
        AND MODULE
-------------------------*/

module ANDMODULE (IN1,IN2,OUT);
    input IN1;
    input IN2;
    output reg OUT;

    always @(IN1,IN2) begin
        if(IN1 & IN2) begin
            OUT = 1'b1;
        end
        else begin
            OUT = 1'b0;
        end
    end
endmodule
/*------------------------
TWOS COMPLIMENT MODULE
-------------------------*/

module TWOS_COMPLIMENT(IN,OUT);
    input[7:0] IN;
    output[7:0] OUT;

    assign #1 OUT = ~IN + 1;
  
endmodule

/*------------------------
        MUX MODULE
-------------------------*/

module MUX (IN1,IN2,OUT,SELECT);
    input[7:0] IN1,IN2;
    input SELECT;
    output reg[7:0] OUT;

    always @(IN1,IN2,SELECT) begin
        case(SELECT)                                   // Select selector bit of multiplexer
            /*If SELECT is high it will select IN1*/
            1'b1    :   assign OUT = IN1;

            /*If SELECT is low it will select IN2*/   
            1'b0    :   assign OUT = IN2;

            /*As the default case this will select IN1*/                            
            default :   assign OUT = IN1;                             

        endcase 
    end
endmodule

/*------------------------
        SHIFT - LEFT  MODULE
-------------------------*/

module  ShiftLeft(SHIFT,SHIFTED);
    input[7:0] SHIFT;
    output signed[9:0] SHIFTED;

    /*Shift the offset by 2*/
    assign SHIFTED = SHIFT << 2;
endmodule

/*------------------------
        EXTEND  MODULE
-------------------------*/

module Extend (EXTEND , EXTENDED);
    input[9:0] EXTEND;
    output signed[31:0] EXTENDED;

    /*Extend the bits upto 32 bits*/
    assign EXTENDED = $signed(EXTEND);

endmodule

/*------------------------
    MUX BRANCH MODULE
-------------------------*/

module MUXBRANCH (IN1,IN2,OUT,SELECT);
    input[31:0] IN1,IN2;
    input SELECT;
    output reg signed[31:0] OUT;

    always @(IN1,IN2,SELECT) begin
        case(SELECT)                                   // Select selector bit of multiplexer
            /*If SELECT is high it will select IN1*/
            1'b1    :   assign OUT = IN1;

            /*If SELECT is low it will select IN2*/   
            1'b0    :   assign OUT = IN2;

            /*As the default case this will select IN1*/                            
            default :   assign OUT = IN1;                             

        endcase 
    end
endmodule

/*------------------------
        adder MODULE
-------------------------*/

module adder (PC,CLK,RESET);
    output reg signed[31:0] PC;
    input CLK,RESET;
    reg signed[31:0] PC_OUT;
    always @(posedge(CLK)) begin
        if (RESET) begin
            #1 PC = 0;
        end
        else begin
            #1 PC = PC_OUT;
        end  
    end
 
    always @(PC) begin
       #1 PC_OUT = PC + 4;
    end

endmodule

/*------------------------
        TRAGET ADDRESS MODULE
-------------------------*/
module TARGET (PCNEXT,SHIFTED_OFFSET,TARGET);
    input[31:0] PCNEXT,SHIFTED_OFFSET;
    output signed[31:0] TARGET ;

    /*GET the targeted address*/
    assign #2 TARGET = PCNEXT + SHIFTED_OFFSET ;
endmodule

/*------------------------
    BranchAdder MODULE
-------------------------*/
module BranchAdder (PC,CLK,RESET,SHIFTED_OFFSET,BRANCH_SELECT,JUMP_ENABLE);
    input[31:0] SHIFTED_OFFSET;
    input CLK,RESET,BRANCH_SELECT,JUMP_ENABLE;
    wire[31:0] TARGET_ADDRESS ;
    wire[31:0] MUX1OUT,MUX2OUT;
    reg[31:0] temp ;
    output reg[31:0] PC;

    /*At the positive edge of the clock PC = 0 */
    always @(posedge(CLK)) begin
        if (RESET) begin
            #1 PC <= 0;
        end

    end
    
    /*PC = PC + 4*/
    always @(PC) begin
       #1 temp <= PC + 4;
    end

    /*Module instantiation to get the target address*/
    TARGET target(temp,SHIFTED_OFFSET,TARGET_ADDRESS) ;

    /*If the BRANCH_SELECT is high it will select TARGET_ADDRESS otherwise PC + 4*/
    MUXBRANCH mbr1(TARGET_ADDRESS,temp,MUX1OUT,BRANCH_SELECT) ;

    /*If teh JUMP_ENABLE is high it will select TARGET_ADDRESS , otherwise PC + 4*/
    MUXBRANCH mbr2(TARGET_ADDRESS,MUX1OUT,MUX2OUT,JUMP_ENABLE) ;

    /*Get the MUX2OUT value to PC*/
    always @(posedge CLK) begin
        PC <= MUX2OUT;
    end
endmodule
/*------------------------
    ControlUnit MODULE
-------------------------*/

module ControlUnit (OPCODE,WRITE_ENABLE,MUX1SELECT,MUX2SELECT,BRANCH_ENABLE,JUMP_ENABLE,ALUOP);
    input[7:0] OPCODE;

    output reg WRITE_ENABLE;
    output reg MUX1SELECT;
    output reg MUX2SELECT;
    output reg BRANCH_ENABLE;
    output reg JUMP_ENABLE;
    output reg[2:0] ALUOP;
    
    always @(OPCODE) begin
        case (OPCODE) 
            /*LOADI Instruction*/
            8'b0000_0000     :       begin
                                        #1
                                          ALUOP = 3'b000;
                                          MUX1SELECT = 1'b1;
                                          MUX2SELECT = 1'b1;
                                          WRITE_ENABLE = 1'b1;
                                          BRANCH_ENABLE = 1'b0;
                                          JUMP_ENABLE = 1'b0;
                                    end

            /*MOV to specific reg*/
            8'b0000_0001    :       begin
                                        #1
                                          ALUOP = 3'b000;
                                          MUX1SELECT = 1'b1;
                                          MUX2SELECT = 1'b0;
                                          WRITE_ENABLE = 1'b1;
                                          BRANCH_ENABLE = 1'b0;
                                          JUMP_ENABLE = 1'b0;
                                    end

            /*ADD instruction*/
            8'b0000_0010    :       begin
                                        #1
                                          ALUOP = 3'b001;
                                          MUX1SELECT = 1'b1;
                                          MUX2SELECT = 1'b0;
                                          WRITE_ENABLE = 1'b1;
                                          BRANCH_ENABLE = 1'b0;  
                                          JUMP_ENABLE = 1'b0;
                                    end
            
            /*SUB instrcution*/
            8'b0000_0011        :   begin
                                        #1
                                          ALUOP = 3'b001;
                                          MUX1SELECT = 1'b0;
                                          MUX2SELECT = 1'b0;
                                          WRITE_ENABLE = 1'b1;
                                          BRANCH_ENABLE = 1'b0;  
                                          JUMP_ENABLE = 1'b0;
                                    end
            
            /*AND instruction*/
            8'b0000_0100    :       begin
                                        #1
                                          ALUOP = 3'b010;
                                          MUX1SELECT = 1'b1;
                                          MUX2SELECT = 1'b0;
                                          WRITE_ENABLE = 1'b1;
                                          BRANCH_ENABLE = 1'b0;  
                                          JUMP_ENABLE = 1'b0;
                                    end

            /*OR instruction*/
            8'b0000_0101    :       begin
                                        #1
                                          ALUOP = 3'b011;
                                          MUX1SELECT = 1'b1;
                                          MUX2SELECT = 1'b0;
                                          WRITE_ENABLE = 1'b1;
                                          BRANCH_ENABLE = 1'b0;  
                                          JUMP_ENABLE = 1'b0; 
                                    end

            /*JUMP instruction*/
            8'b0000_0110         :       begin
                                        #1
                                         ALUOP = 3'b000;
                                         MUX1SELECT = 1'b1;
                                         MUX2SELECT = 1'b0;
                                         WRITE_ENABLE = 1'b0; 
                                         BRANCH_ENABLE = 1'b0;
                                         JUMP_ENABLE = 1'b1;
                                    end
            
            /*BEQ instruction*/
            8'b0000_0111         :       begin
                                        #1
                                         ALUOP = 3'b001;
                                         MUX1SELECT = 1'b0;
                                         MUX2SELECT = 1'b0;
                                         WRITE_ENABLE = 1'b0; 
                                         BRANCH_ENABLE = 1'b1;
                                         JUMP_ENABLE = 1'b0;
                                    end
                                     
        endcase
    end

endmodule

Lab 05/group19_lab5_part4/reg.v
/*
Group 19
Lab05 - Part02
*/

module reg_file (IN , OUT1 , OUT2 , INADDRESS , OUT1ADDRESS , OUT2ADDRESS , WRITE , CLK , RESET);
    
    /*Inputs*/
    input[7:0] IN ;
    input[2:0] INADDRESS ;
    input[2:0] OUT1ADDRESS  , OUT2ADDRESS ;
    input WRITE , CLK , RESET ;

    /*Outputs*/
    output reg[7:0] OUT1 , OUT2 ;
    
    /*Registers from 0 - 7*/
    reg[7:0] register[7:0] ;

    /*Int variable*/
    integer i;

    always @(posedge(CLK)) begin
        
        /*If the RESET is high , all the registers will be set to zero*/
        if (RESET) begin
            #1
            for (i= 0; i <= 7 ;i+=1 ) begin
                register[i] <=  0 ;
            end
        end

        /*If the WRITE_ENABLE is high*/

        else if (WRITE) begin
            #1 register[INADDRESS] <= IN ;
        end
    end

    /*
    If any of the inputs were changed
    */
    
    always @(OUT1ADDRESS,OUT2ADDRESS,register[0],register[1],register[2],register[3],register[4],register[5],register[6],register[7])        
            begin
            #2 OUT1 <= register[OUT1ADDRESS] ;
               OUT2 <= register[OUT2ADDRESS] ; 
    end

    initial
	begin
		#5
		$display("\n\t\t\t==================================================================");
		$display("\t\t\t Change of Register Content Starting from Time #5");
		$display("\t\t\t==================================================================\n");
		$display("\t\ttime\tregs0\tregs1\tregs2\tregs3\tregs4\tregs5\tregs6\tregs7");
		$display("\t\t-------------------------------------------------------------------------------------");
		$monitor($time, "\t%d\t%d\t%d\t%d\t%d\t%d\t%d\t%d", register[0], register[1], register[2], register[3], register[4], register[5], register[6], register[7]);
	end

    /*Ignore the warnings
    This will also include the values in registers to the same .vcd file*/
    initial begin
        $dumpfile("cpu_wavedata.vcd") ;
        
        for (i = 0;i<8 ; i+=1)
            $dumpvars(1,register[i]) ;
        
    end

endmodule

Lab 05/group19_lab5_part4/cpu_tb.v
// Computer Architecture (CO224) - Lab 05
// Design: Testbench of Integrated CPU of Simple Processor
// Author: Isuru Nawinne
`include "cpu.v"

module cpu_tb;

    reg CLK, RESET;
    wire [31:0] PC;
    reg [31:0] INSTRUCTION;
    
    /* 
    ------------------------
     SIMPLE INSTRUCTION MEM
    ------------------------
    */
    
    // TODO: Initialize an array of registers (8x1024) named 'instr_mem' to be used as instruction memory
    reg[7:0] instr_mem[1023:0];
    
    // TODO: Create combinational logic to support CPU instruction fetching, given the Program Counter(PC) value 
    //       (make sure you include the delay for instruction fetching here)
    always @(PC) begin
        #2 INSTRUCTION = {instr_mem[PC+3],instr_mem[PC+2],instr_mem[PC+1],instr_mem[PC]} ;
    end

    initial
    begin
        // Initialize instruction memory with the set of instructions you need execute on CPU
        
        // METHOD 1: manually loading instructions to instr_mem
        //{instr_mem[10'd3], instr_mem[10'd2], instr_mem[10'd1], instr_mem[10'd0]} = 32'b00000000000001000000000000000101;
        //{instr_mem[10'd7], instr_mem[10'd6], instr_mem[10'd5], instr_mem[10'd4]} = 32'b00000000000000100000000000001001;
        //{instr_mem[10'd11], instr_mem[10'd10], instr_mem[10'd9], instr_mem[10'd8]} = 32'b00000010000001100000010000000010;
        /* {instr_mem[10'd3], instr_mem[10'd2], instr_mem[10'd1], instr_mem[10'd0]} = 32'b00000000000001000000000000000101;            // loadi 4 5
        {instr_mem[10'd7], instr_mem[10'd6], instr_mem[10'd5], instr_mem[10'd4]} = 32'b00000000000000100000000000001001;            // loadi 2 9
        {instr_mem[10'd11], instr_mem[10'd10], instr_mem[10'd9], instr_mem[10'd8]} = 32'b00000010000001100000010000000010;          // add 6 2 4
        {instr_mem[10'd15], instr_mem[10'd14], instr_mem[10'd13], instr_mem[10'd12]} = 32'b00000000000000010000000000000101;        // loadi 1 5
        {instr_mem[10'd19], instr_mem[10'd18], instr_mem[10'd17], instr_mem[10'd16]} = 32'b00000111000000100000000100000100;        // beq 0x2 1 4
        {instr_mem[10'd23], instr_mem[10'd22], instr_mem[10'd21], instr_mem[10'd20]} = 32'b00000000000001000000000000000111;        // loadi 4 7
        {instr_mem[10'd27], instr_mem[10'd26], instr_mem[10'd25], instr_mem[10'd24]} = 32'b00000000000001000000000000001101;        // loadi 4 13
        {instr_mem[10'd31], instr_mem[10'd30], instr_mem[10'd29], instr_mem[10'd28]} = 32'b00000000000001000000000000001111;        // loadi 4 15
        {instr_mem[10'd35], instr_mem[10'd34], instr_mem[10'd33], instr_mem[10'd32]} = 32'b00000000000001000000000000001011;        // loadi 4 11
        {instr_mem[10'd39], instr_mem[10'd38], instr_mem[10'd37], instr_mem[10'd36]} = 32'b00000110000000100000000000001011;        // j 0x2
        {instr_mem[10'd43], instr_mem[10'd42], instr_mem[10'd41], instr_mem[10'd40]} = 32'b00000000000001000000000000101101;        // loadi 4 45
        {instr_mem[10'd47], instr_mem[10'd46], instr_mem[10'd45], instr_mem[10'd44]} = 32'b00000000000001000000000000011111;        // loadi 4 31
        {instr_mem[10'd51], instr_mem[10'd50], instr_mem[10'd49], instr_mem[10'd48]} = 32'b00000000000001000000000000011011;        // loadi 4 27 */

        // METHOD 2: loading instr_mem content from instr_mem.mem file
        $readmemb("instr_mem.mem", instr_mem);
    end
    
    /* 
    -----
     CPU
    -----
    */
    cpu mycpu(PC, INSTRUCTION, CLK, RESET);

    initial
    begin
    
        // generate files needed to plot the waveform using GTKWave
        $dumpfile("cpu_wavedata.vcd");
		$dumpvars(0, cpu_tb);
        
        CLK = 1'b0;
        //RESET = 1'b0;
        
        // TODO: Reset the CPU (by giving a pulse to RESET signal) to start the program execution
        
        RESET = 1'b1;
        
        #10
        RESET = 1'b0; 

        #500
        $finish;
        
    end
    
    // clock signal generation
    always
        #4 CLK = ~CLK;
        

endmodule

Lab 05/group19_lab5_part4/cpu_wavedata.vcd
$date
	Sun Feb 27 16:44:50 2022
$end
$version
	Icarus Verilog
$end
$timescale
	1s
$end
$scope module cpu_tb $end
$scope module mycpu $end
$scope module register $end
$var reg 8 ! \register[0] [7:0] $end
$upscope $end
$upscope $end
$upscope $end
$scope module cpu_tb $end
$scope module mycpu $end
$scope module register $end
$var reg 8 " \register[1] [7:0] $end
$upscope $end
$upscope $end
$upscope $end
$scope module cpu_tb $end
$scope module mycpu $end
$scope module register $end
$var reg 8 # \register[2] [7:0] $end
$upscope $end
$upscope $end
$upscope $end
$scope module cpu_tb $end
$scope module mycpu $end
$scope module register $end
$var reg 8 $ \register[3] [7:0] $end
$upscope $end
$upscope $end
$upscope $end
$scope module cpu_tb $end
$scope module mycpu $end
$scope module register $end
$var reg 8 % \register[4] [7:0] $end
$upscope $end
$upscope $end
$upscope $end
$scope module cpu_tb $end
$scope module mycpu $end
$scope module register $end
$var reg 8 & \register[5] [7:0] $end
$upscope $end
$upscope $end
$upscope $end
$scope module cpu_tb $end
$scope module mycpu $end
$scope module register $end
$var reg 8 ' \register[6] [7:0] $end
$upscope $end
$upscope $end
$upscope $end
$scope module cpu_tb $end
$scope module mycpu $end
$scope module register $end
$var reg 8 ( \register[7] [7:0] $end
$upscope $end
$upscope $end
$upscope $end
$scope module cpu_tb $end
$var wire 32 ) PC [31:0] $end
$var reg 1 * CLK $end
$var reg 32 + INSTRUCTION [31:0] $end
$var reg 1 , RESET $end
$scope module mycpu $end
$var wire 1 * CLK $end
$var wire 32 - INSTRUCTION [31:0] $end
$var wire 1 , RESET $end
$var wire 1 . ZERO $end
$var wire 1 / WRITE_ENABLE $end
$var wire 10 0 SHIFTED [9:0] $end
$var wire 32 1 PC [31:0] $end
$var wire 8 2 OUT2 [7:0] $end
$var wire 8 3 OUT1 [7:0] $end
$var wire 8 4 NEG [7:0] $end
$var wire 1 5 MUX2SELECT $end
$var wire 8 6 MUX2OUT [7:0] $end
$var wire 1 7 MUX1SELECT $end
$var wire 8 8 MUX1OUT [7:0] $end
$var wire 1 9 JUMP_ENABLE $end
$var wire 32 : EXTENDED [31:0] $end
$var wire 1 ; BRANCH_SELECT $end
$var wire 1 < BRANCH_ENABLE $end
$var wire 8 = ALURESULT [7:0] $end
$var wire 3 > ALUOP [2:0] $end
$var reg 8 ? IMMEDIATE [7:0] $end
$var reg 8 @ OFFSET [7:0] $end
$var reg 8 A OPCODE [7:0] $end
$var reg 3 B READREG1 [2:0] $end
$var reg 3 C READREG2 [2:0] $end
$var reg 3 D WRITEREG [2:0] $end
$scope module alu $end
$var wire 8 E resultOR [7:0] $end
$var wire 8 F resultFORWARD [7:0] $end
$var wire 8 G resultAND [7:0] $end
$var wire 8 H resultADD [7:0] $end
$var wire 3 I SELECT [2:0] $end
$var wire 8 J DATA2 [7:0] $end
$var wire 8 K DATA1 [7:0] $end
$var reg 8 L RESULT [7:0] $end
$var reg 1 . ZERO $end
$scope module add1 $end
$var wire 8 M RESULT [7:0] $end
$var wire 8 N DATA2 [7:0] $end
$var wire 8 O DATA1 [7:0] $end
$upscope $end
$scope module and1 $end
$var wire 8 P RESULT [7:0] $end
$var wire 8 Q DATA2 [7:0] $end
$var wire 8 R DATA1 [7:0] $end
$upscope $end
$scope module forward1 $end
$var wire 8 S RESULT [7:0] $end
$var wire 8 T DATA2 [7:0] $end
$upscope $end
$scope module or1 $end
$var wire 8 U RESULT [7:0] $end
$var wire 8 V DATA2 [7:0] $end
$var wire 8 W DATA1 [7:0] $end
$upscope $end
$upscope $end
$scope module andmodule $end
$var wire 1 . IN1 $end
$var wire 1 < IN2 $end
$var reg 1 ; OUT $end
$upscope $end
$scope module beqadder $end
$var wire 1 ; BRANCH_SELECT $end
$var wire 1 * CLK $end
$var wire 1 , RESET $end
$var wire 32 X TARGET_ADDRESS [31:0] $end
$var wire 32 Y SHIFTED_OFFSET [31:0] $end
$var wire 32 Z MUX2OUT [31:0] $end
$var wire 32 [ MUX1OUT [31:0] $end
$var wire 1 9 JUMP_ENABLE $end
$var reg 32 \ PC [31:0] $end
$var reg 32 ] temp [31:0] $end
$scope module mbr1 $end
$var wire 32 ^ IN2 [31:0] $end
$var wire 1 ; SELECT $end
$var wire 32 _ IN1 [31:0] $end
$var reg 32 ` OUT [31:0] $end
$upscope $end
$scope module mbr2 $end
$var wire 32 a IN2 [31:0] $end
$var wire 1 9 SELECT $end
$var wire 32 b IN1 [31:0] $end
$var reg 32 c OUT [31:0] $end
$upscope $end
$scope module target $end
$var wire 32 d PCNEXT [31:0] $end
$var wire 32 e TARGET [31:0] $end
$var wire 32 f SHIFTED_OFFSET [31:0] $end
$upscope $end
$upscope $end
$scope module cu $end
$var wire 8 g OPCODE [7:0] $end
$var reg 3 h ALUOP [2:0] $end
$var reg 1 < BRANCH_ENABLE $end
$var reg 1 9 JUMP_ENABLE $end
$var reg 1 7 MUX1SELECT $end
$var reg 1 5 MUX2SELECT $end
$var reg 1 / WRITE_ENABLE $end
$upscope $end
$scope module ex $end
$var wire 32 i EXTENDED [31:0] $end
$var wire 10 j EXTEND [9:0] $end
$upscope $end
$scope module f1 $end
$var wire 8 k OUT [7:0] $end
$var wire 8 l IN [7:0] $end
$upscope $end
$scope module m1 $end
$var wire 8 m IN2 [7:0] $end
$var wire 1 7 SELECT $end
$var wire 8 n IN1 [7:0] $end
$var reg 8 o OUT [7:0] $end
$upscope $end
$scope module m2 $end
$var wire 8 p IN1 [7:0] $end
$var wire 8 q IN2 [7:0] $end
$var wire 1 5 SELECT $end
$var reg 8 r OUT [7:0] $end
$upscope $end
$scope module register $end
$var wire 1 * CLK $end
$var wire 8 s IN [7:0] $end
$var wire 3 t INADDRESS [2:0] $end
$var wire 3 u OUT1ADDRESS [2:0] $end
$var wire 3 v OUT2ADDRESS [2:0] $end
$var wire 1 , RESET $end
$var wire 1 / WRITE $end
$var reg 8 w OUT1 [7:0] $end
$var reg 8 x OUT2 [7:0] $end
$var integer 32 y i [31:0] $end
$upscope $end
$scope module sl $end
$var wire 8 z SHIFT [7:0] $end
$var wire 10 { SHIFTED [9:0] $end
$upscope $end
$upscope $end
$upscope $end
$enddefinitions $end
#0
$dumpvars
bx00 {
bx z
b1000 y
bx x
bx w
bx v
bx u
bx t
bx s
bx r
bx q
bx p
bx o
bx n
bx m
bx l
bx k
bx00 j
bx00 i
bx h
bx g
bx00 f
bx e
bx d
bx c
bx b
bx a
bx `
bx _
bx ^
bx ]
bx \
bx [
bx Z
bx00 Y
bx X
bx W
bx V
bx U
bx T
bx S
bx R
bx Q
bx P
bx O
bx N
bx M
bx L
bx K
bx J
bx I
bx H
bx G
bx F
bx E
bx D
bx C
bx B
bx A
bx @
bx ?
bx >
bx =
x<
x;
bx00 :
x9
bx 8
x7
bx 6
x5
bx 4
bx 3
bx 2
bx 1
bx00 0
x/
x.
bx -
1,
bx +
0*
bx )
bx (
bx '
bx &
bx %
bx $
bx #
bx "
bx !
$end
#4
1*
#5
b0 )
b0 1
b0 \
b0 (
b0 '
b0 &
b0 %
b0 $
b0 #
b0 "
b0 !
b1000 y
#6
b100 ]
b100 ^
b100 d
#7
b100 [
b100 `
b100 a
0;
0.
b10000 :
b10000 Y
b10000 f
b10000 i
b10000 0
b10000 j
b10000 {
b1010 6
b1010 J
b1010 N
b1010 Q
b1010 T
b1010 V
b1010 r
b100 @
b100 z
b1010 ?
b1010 p
b10 C
b10 v
b0 B
b0 u
b100 D
b100 t
b0 A
b0 g
b1000000000000001010 +
b1000000000000001010 -
#8
b100 Z
b100 c
b1010 =
b1010 L
b1010 s
bx1x1x E
bx1x1x U
b0x0x0 G
b0x0x0 P
b1010 F
b1010 S
09
0<
1/
15
17
b0 >
b0 I
b0 h
0*
#9
b0 8
b0 o
b0 q
b0 2
b0 l
b0 n
b0 x
b0 3
b0 K
b0 O
b0 R
b0 W
b0 w
b10100 X
b10100 _
b10100 b
b10100 e
#10
b0 4
b0 k
b0 m
b1010 E
b1010 U
b0 G
b0 P
0,
#11
b1010 H
b1010 M
#12
b100 )
b100 1
b100 \
1*
#13
b1000 Z
b1000 c
b1000 [
b1000 `
b1000 a
b1000 ]
b1000 ^
b1000 d
b1010 %
#14
b10100 :
b10100 Y
b10100 f
b10100 i
b10100 0
b10100 j
b10100 {
b101 @
b101 z
b1 6
b1 J
b1 N
b1 Q
b1 T
b1 V
b1 r
b1 ?
b1 p
b1 C
b1 v
b101 D
b101 t
b1010000000000000001 +
b1010000000000000001 -
#15
b1 E
b1 U
b1 =
b1 L
b1 s
b1 F
b1 S
#16
b11100 X
b11100 _
b11100 b
b11100 e
b1 H
b1 M
0*
#20
b1000 )
b1000 1
b1000 \
1*
#21
b1100 Z
b1100 c
b1100 [
b1100 `
b1100 a
b1100 ]
b1100 ^
b1100 d
b1 &
#22
b11000 :
b11000 Y
b11000 f
b11000 i
b11000 0
b11000 j
b11000 {
b110 @
b110 z
b110 D
b110 t
b1100000000000000001 +
b1100000000000000001 -
#24
b100100 X
b100100 _
b100100 b
b100100 e
0*
#28
b1100 )
b1100 1
b1100 \
1*
#29
b10000 Z
b10000 c
b10000 [
b10000 `
b10000 a
b10000 ]
b10000 ^
b10000 d
b1 '
#30
b11100 :
b11100 Y
b11100 f
b11100 i
b11100 0
b11100 j
b11100 {
b111 @
b111 z
b1001 6
b1001 J
b1001 N
b1001 Q
b1001 T
b1001 V
b1001 r
b1001 ?
b1001 p
b111 D
b111 t
b1110000000000001001 +
b1110000000000001001 -
#31
b1001 E
b1001 U
b1001 =
b1001 L
b1001 s
b1001 F
b1001 S
#32
b101100 X
b101100 _
b101100 b
b101100 e
b1001 H
b1001 M
0*
#36
b10000 )
b10000 1
b10000 \
1*
#37
b10100 Z
b10100 c
b10100 [
b10100 `
b10100 a
b10100 ]
b10100 ^
b10100 d
b1001 (
#38
b10000 :
b10000 Y
b10000 f
b10000 i
b10000 0
b10000 j
b10000 {
b100 @
b100 z
b101 6
b101 J
b101 N
b101 Q
b101 T
b101 V
b101 r
b101 ?
b101 p
b101 C
b101 v
b100 B
b100 u
b100 D
b100 t
b11 A
b11 g
b11000001000000010000000101 +
b11000001000000010000000101 -
#39
b1 2
b1 l
b1 n
b1 x
b1010 3
b1010 K
b1010 O
b1010 R
b1010 W
b1010 w
b0 6
b0 J
b0 N
b0 Q
b0 T
b0 V
b0 r
b101 E
b101 U
05
07
b1 >
b1 I
b1 h
b1001 =
b1001 L
b1001 s
b101 F
b101 S
#40
b11111111 6
b11111111 J
b11111111 N
b11111111 Q
b11111111 T
b11111111 V
b11111111 r
b11111111 8
b11111111 o
b11111111 q
b11111111 4
b11111111 k
b11111111 m
b1010 E
b1010 U
b0 F
b0 S
b100100 X
b100100 _
b100100 b
b100100 e
0*
#41
b11111111 E
b11111111 U
b1010 G
b1010 P
b11111111 F
b11111111 S
#44
b10100 )
b10100 1
b10100 \
1*
#45
b11000 Z
b11000 c
b11000 [
b11000 `
b11000 a
b11000 ]
b11000 ^
b11000 d
b1001 %
#46
b100 :
b100 Y
b100 f
b100 i
b100 0
b100 j
b100 {
b1 @
b1 z
b110 ?
b110 p
b110 C
b110 v
b1 D
b1 t
b111 A
b111 g
b111000000010000010000000110 +
b111000000010000010000000110 -
#47
b1001 3
b1001 K
b1001 O
b1001 R
b1001 W
b1001 w
1<
0/
#48
b1001 G
b1001 P
b11100 X
b11100 _
b11100 b
b11100 e
0*
#49
b1000 =
b1000 L
b1000 s
b1000 H
b1000 M
#52
b11000 )
b11000 1
b11000 \
1*
#53
b11100 Z
b11100 c
b11100 [
b11100 `
b11100 a
b11100 ]
b11100 ^
b11100 d
#54
b11111111111111111111111111110100 :
b11111111111111111111111111110100 Y
b11111111111111111111111111110100 f
b11111111111111111111111111110100 i
b1111110100 0
b1111110100 j
b1111110100 {
b11111101 @
b11111101 z
b0 ?
b0 p
b0 C
b0 v
b0 B
b0 u
b101 D
b101 t
b110 A
b110 g
b110111111010000000000000000 +
b110111111010000000000000000 -
#55
b1 6
b1 J
b1 N
b1 Q
b1 T
b1 V
b1 r
b1 8
b1 o
b1 q
b11111111 =
b11111111 L
b11111111 s
19
0<
17
b0 >
b0 I
b0 h
